[ {
  "id" : "0e0dff4c-6122-4c75-b223-c662aafe231b",
  "createdAt" : "2021-01-02 19:11",
  "active" : true,
  "name" : "Default",
  "discount" : 0,
  "minimumPoints" : 0
}, {
  "id" : "0790e505-8ed6-4143-bb03-212b771aabca",
  "createdAt" : "2021-01-02 19:11",
  "active" : true,
  "name" : "Bronze",
  "discount" : 3,
  "minimumPoints" : 1000
}, {
  "id" : "58dbb72f-80f8-4a85-a98f-53e75380b2e8",
  "createdAt" : "2021-01-02 19:11",
  "active" : true,
  "name" : "Gold",
  "discount" : 10,
  "minimumPoints" : 2000
}, {
  "id" : "66794ee1-d70a-41f9-b740-2ffd4167594e",
  "createdAt" : "2021-01-02 19:11",
  "active" : true,
  "name" : "Silver",
  "discount" : 5,
  "minimumPoints" : 1500
} ]